vibe_farm/__about__.py
vibe_farm/__init__.py
vibe_farm/__main__.py
vibe_farm/analysis/__init__.py
vibe_farm/analysis/ast_utils.py
vibe_farm/code.py
vibe_farm/commands/__init__.py
vibe_farm/commands/analyze.py
vibe_farm/commands/compile.py
vibe_farm/commands/context.py
vibe_farm/commands/utils.py
vibe_farm/compiler/__init__.py
vibe_farm/compiler/context.py
vibe_farm/compiler/plots.py
vibe_farm/compiler/prompt.py
vibe_farm/compiler/providers.py
vibe_farm/compiler/sanitizers.py
vibe_farm/compiler/verification.py
vibe_farm/dependencies.py
vibe_farm/farm.py
vibe_farm/py.typed
vibe_farm-0.1.4.dist-info/LICENSE
vibe_farm-0.1.4.dist-info/METADATA
vibe_farm-0.1.4.dist-info/WHEEL
vibe_farm-0.1.4.dist-info/entry_points.txt
vibe_farm-0.1.4.dist-info/RECORD
