Metadata-Version: 2.3
Name: vibe_farm
Version: 0.1.4
Summary: A Python project in a dev container.
License: MIT License
Keywords: python,development,tools
Author: Kris Jordan
Author-email: kris@example.com
Requires-Python: >=3.12
Classifier: Development Status :: 3 - Alpha
Classifier: Intended Audience :: Developers
Classifier: License :: OSI Approved :: MIT License
Classifier: Programming Language :: Python :: 3
Classifier: Programming Language :: Python :: 3.12
Classifier: Typing :: Typed
Provides-Extra: dev
Requires-Dist: anthropic
Requires-Dist: black ; extra == "dev"
Requires-Dist: mypy ; extra == "dev"
Requires-Dist: nox ; extra == "dev"
Requires-Dist: openai
Requires-Dist: pytest ; extra == "dev"
Requires-Dist: pytest-cov ; extra == "dev"
Requires-Dist: python-dotenv
